{
  "id": "test057",
  "images": [
    "http://n8n.autoreel.io.vn:8188/view?filename=test057_00001_.png&subfolder=&type=output",
    "http://n8n.autoreel.io.vn:8188/view?filename=test057_00002_.png&subfolder=&type=output",
    "http://n8n.autoreel.io.vn:8188/view?filename=test057_00003_.png&subfolder=&type=output",
    "http://n8n.autoreel.io.vn:8188/view?filename=test057_00004_.png&subfolder=&type=output",
    "http://n8n.autoreel.io.vn:8188/view?filename=test057_00005_.png&subfolder=&type=output",
    "http://n8n.autoreel.io.vn:8188/view?filename=test057_00006_.png&subfolder=&type=output",
    "http://n8n.autoreel.io.vn:8188/view?filename=test057_00007_.png&subfolder=&type=output",
    "http://n8n.autoreel.io.vn:8188/view?filename=test057_00008_.png&subfolder=&type=output",
    "http://n8n.autoreel.io.vn:8188/view?filename=test057_00009_.png&subfolder=&type=output",
    "http://n8n.autoreel.io.vn:8188/view?filename=test057_00010_.png&subfolder=&type=output",
    "http://n8n.autoreel.io.vn:8188/view?filename=test057_00011_.png&subfolder=&type=output",
    "http://n8n.autoreel.io.vn:8188/view?filename=test057_00012_.png&subfolder=&type=output",
    "http://n8n.autoreel.io.vn:8188/view?filename=test057_00013_.png&subfolder=&type=output",
    "http://n8n.autoreel.io.vn:8188/view?filename=test057_00014_.png&subfolder=&type=output",
    "http://n8n.autoreel.io.vn:8188/view?filename=test057_00015_.png&subfolder=&type=output",
    "http://n8n.autoreel.io.vn:8188/view?filename=test057_00016_.png&subfolder=&type=output",
    "http://n8n.autoreel.io.vn:8188/view?filename=test057_00017_.png&subfolder=&type=output"
  ],
  "durations": [
    "3.920",
    "4.600",
    "3.160",
    "5.200",
    "5.040",
    "3.080",
    "2.840",
    "7.280",
    "3.600",
    "6.320",
    "4.040",
    "5.800",
    "5.560",
    "5.600",
    "3.280",
    "5.960",
    "8.840"
  ],
  "voiceUrl": "https://storage.googleapis.com/autoreel-n8n/test057/voice.mp3",
  "bgUrl": "https://storage.googleapis.com/autoreel-n8n/background-music.mp3",
  "subtitleUrl": "https://storage.googleapis.com/autoreel-n8n/test057/subtitle.srt"
}